eventloop/__init__.py
eventloop/__main__.py
eventloop/base.py
eventloop/common.py
eventloop/ps.py
eventloop/qt.py
eventloop/qta.py
eventloop/test.py
eventloop/uv.py
eventloop/onchange/__init__.py
eventloop/onchange/__main__.py
eventloop-0.0.26.dist-info/LICENSE
eventloop-0.0.26.dist-info/METADATA
eventloop-0.0.26.dist-info/WHEEL
eventloop-0.0.26.dist-info/entry_points.txt
eventloop-0.0.26.dist-info/top_level.txt
eventloop-0.0.26.dist-info/RECORD
