Metadata-Version: 2.2
Name: eventloop
Version: 0.0.26
Summary: Abstraction layer for filesystem events
Home-page: https://github.com/mugiseyebrows/event-loop
Author: Stanislav Doronin
Author-email: mugisbrows@gmail.com
License-File: LICENSE
Requires-Dist: colorama
Dynamic: author
Dynamic: author-email
Dynamic: description
Dynamic: home-page
Dynamic: requires-dist
Dynamic: summary
